phylogemetric/__init__.py
phylogemetric/delta.py
phylogemetric/dist.py
phylogemetric/metric.py
phylogemetric/qresidual.py
phylogemetric/bin/__init__.py
phylogemetric/bin/create_random_nexus.py
phylogemetric/bin/phylogemetric.py
phylogemetric/data/test.nex
phylogemetric/tests/__init__.py
phylogemetric/tests/conftest.py
phylogemetric/tests/data_complex.py
phylogemetric/tests/data_simple.py
phylogemetric/tests/test_bin.py
phylogemetric/tests/test_delta.py
phylogemetric/tests/test_dist.py
phylogemetric/tests/test_metric.py
phylogemetric/tests/test_parallel.py
phylogemetric/tests/test_qresidual.py
phylogemetric-1.2.2.dist-info/LICENSE
phylogemetric-1.2.2.dist-info/METADATA
phylogemetric-1.2.2.dist-info/WHEEL
phylogemetric-1.2.2.dist-info/entry_points.txt
phylogemetric-1.2.2.dist-info/top_level.txt
phylogemetric-1.2.2.dist-info/zip-safe
phylogemetric-1.2.2.dist-info/RECORD
